tree_sitter_t32/__init__.py
tree_sitter_t32/__init__.pyi
tree_sitter_t32/_binding.abi3.so
tree_sitter_t32/binding.c
tree_sitter_t32/py.typed
tree_sitter_t32/queries/folds.scm
tree_sitter_t32/queries/highlights.scm
tree_sitter_t32/queries/injections.scm
tree_sitter_t32/queries/locals.scm
tree_sitter_t32/queries/tags.scm
tree_sitter_t32-7.2.1.dist-info/METADATA
tree_sitter_t32-7.2.1.dist-info/WHEEL
tree_sitter_t32-7.2.1.dist-info/top_level.txt
tree_sitter_t32-7.2.1.dist-info/RECORD
tree_sitter_t32-7.2.1.dist-info/licenses/LICENSES/BSD-2-Clause.txt
tree_sitter_t32-7.2.1.dist-info/licenses/LICENSES/MIT.txt
