Metadata-Version: 2.4
Name: tree-sitter-t32
Version: 7.2.1
Summary: Lauterbach TRACE32® script language grammar for Tree-sitter
Author-email: Christoph Sax <c_sax@mailbox.org>
License-Expression: MIT AND BSD-2-Clause
Project-URL: Homepage, https://codeberg.org/xasc/tree-sitter-t32
Project-URL: Repository, https://codeberg.org/xasc/tree-sitter-t32.git
Project-URL: Issues, https://codeberg.org/xasc/tree-sitter-t32/issues
Project-URL: Changelog, https://codeberg.org/xasc/tree-sitter-t32/src/branch/main/CHANGELOG.md
Keywords: lexer,incremental,parsing,tree-sitter,trace32,t32,lauterbach,practice
Classifier: Intended Audience :: Developers
Classifier: Topic :: Software Development :: Compilers
Classifier: Topic :: Software Development :: Debuggers
Classifier: Topic :: Text Processing :: Linguistic
Classifier: Typing :: Typed
Requires-Python: >=3.10
License-File: LICENSES/BSD-2-Clause.txt
License-File: LICENSES/MIT.txt
Provides-Extra: core
Requires-Dist: tree-sitter~=0.25; extra == "core"
Dynamic: license-file
